mite_extras/__init__.py
mite_extras/main.py
mite_extras/cli/__init__.py
mite_extras/cli/cli_manager.py
mite_extras/processing/__init__.py
mite_extras/processing/data_classes.py
mite_extras/processing/file_manager.py
mite_extras/processing/mite_parser.py
mite_extras/processing/validation_manager.py
mite_extras-1.6.3.dist-info/METADATA
mite_extras-1.6.3.dist-info/WHEEL
mite_extras-1.6.3.dist-info/entry_points.txt
mite_extras-1.6.3.dist-info/licenses/LICENSE
mite_extras-1.6.3.dist-info/RECORD
