Metadata-Version: 2.4
Name: mite_extras
Version: 1.6.3
Summary: Parsing, conversion, and validation functionality for Minimum Information about a Tailoring Enzyme (MITE) files.
Project-URL: Homepage, https://mite.bioinformatics.nl/
Project-URL: Github, https://github.com/mite-standard/mite_extras
Project-URL: Issues, https://github.com/mite-standard/mite_extras/issues
Author-email: "Mitja M. Zdouc" <zdoucmm@gmail.com>, Adriano Rutz <adafede@gmail.com>
License-File: LICENSE
Keywords: cheminformatics,genomics
Classifier: Development Status :: 4 - Beta
Classifier: License :: OSI Approved :: MIT License
Classifier: Operating System :: POSIX :: Linux
Classifier: Programming Language :: Python :: 3.12
Classifier: Topic :: Scientific/Engineering :: Bio-Informatics
Classifier: Topic :: Scientific/Engineering :: Chemistry
Requires-Python: <3.13.0,>=3.12.0
Requires-Dist: argparse~=1.4
Requires-Dist: coloredlogs~=15.0
Requires-Dist: json-repair~=0.51
Requires-Dist: jsonschema~=4.25
Requires-Dist: mite-schema
Requires-Dist: pydantic~=2.11
Requires-Dist: rdkit==2024.3.6
Requires-Dist: requests~=2.32
Provides-Extra: dev
Requires-Dist: pre-commit~=4.3; extra == 'dev'
Requires-Dist: pytest~=8.4; extra == 'dev'
Requires-Dist: ruff~=0.13; extra == 'dev'
